{
  "project_info": {
    "project_number": "707900993259",
    "project_id": "mapline-android"
  },
  "client": [
    {
      "client_info": {
        "mobilesdk_app_id": "1:707900993259:android:c70db5b3de017e8a",
        "android_client_info": {
          "package_name": "br.com.fiap.mapline"
        }
      },
      "oauth_client": [
        {
          "client_id": "707900993259-s0riv65tpkkuatj9dn17e84ba74ls6sg.apps.googleusercontent.com",
          "client_type": 1,
          "android_info": {
            "package_name": "br.com.fiap.mapline",
            "certificate_hash": "26E54E43DFE9AB9ABD234F5DCBCADBD948A8E15D"
          }
        },
        {
          "client_id": "707900993259-f5ib2krb5adhmn53igar0cn2lggvonve.apps.googleusercontent.com",
          "client_type": 3
        }
      ],
      "api_key": [
        {
          "current_key": "AIzaSyDJ3kjj4b1n8ohGnrgz2TOKxdmG-xJhDIk"
        }
      ],
      "services": {
        "analytics_service": {
          "status": 1
        },
        "appinvite_service": {
          "status": 1,
          "other_platform_oauth_client": []
        },
        "ads_service": {
          "status": 1
        }
      }
    }
  ],
  "configuration_version": "1"
}